jscatter-1.8.1.dist-info/RECORD
jscatter-1.8.1.dist-info/WHEEL
jscatter-1.8.1.dist-info/top_level.txt
jscatter-1.8.1.dist-info/METADATA
jscatter-1.8.1.dist-info/licenses/src/jscatter/LICENSE
jscatter/tipsreadme.rst
jscatter/dls.py
jscatter/LICENSE
jscatter/CHANGELOG
jscatter/dataarray.py
jscatter/sasimagelib.py
jscatter/__init__.py
jscatter/TODO
jscatter/mpl.py
jscatter/INSTALLATION.txt
jscatter/README.rst
jscatter/parallel.py
jscatter/graceplot.py
jscatter/smallanglescattering.py
jscatter/bio/mda.py
jscatter/bio/nma.py
jscatter/bio/createResidueFFAmp.py
jscatter/bio/__init__.py
jscatter/bio/scatter.py
jscatter/bio/utilities.py
jscatter/dynamic/__init__.py
jscatter/dynamic/frequencydomain.py
jscatter/dynamic/timedomain.py
jscatter/dynamic/fft.py
jscatter/test/contourImage.jpg
jscatter/test/__init__.py
jscatter/test/test.py
jscatter/test/test_imagehash.py
jscatter/structurefactor/lattices.py
jscatter/structurefactor/__init__.py
jscatter/structurefactor/ordered.py
jscatter/structurefactor/fluid.py
jscatter/formel/functions.py
jscatter/formel/quadrature.py
jscatter/formel/formel.py
jscatter/formel/__init__.py
jscatter/formel/physics.py
jscatter/source/CMakeLists.txt
jscatter/source/erfr.f90
jscatter/source/a_qshep3d.f95
jscatter/source/autil.f95
jscatter/source/__init__.py
jscatter/source/a_typesandconstants.f95
jscatter/source/SASA_surface.c
jscatter/source/a_halton.f95
jscatter/source/dynamic.f95
jscatter/source/cloud.f95
jscatter/.dylibs/libgfortran.5.dylib
jscatter/.dylibs/libquadmath.0.dylib
jscatter/.dylibs/libgcc_s.1.1.dylib
jscatter/.dylibs/libgomp.1.dylib
jscatter/libs/imagehash.py
jscatter/libs/SASAsurface.py
jscatter/libs/Two_Yukawa.py
jscatter/libs/ml_internal.py
jscatter/libs/surface.cpython-311-darwin.so
jscatter/libs/__init__.py
jscatter/libs/fscatter.cpython-311-darwin.so
jscatter/libs/HullRad.py
jscatter/libs/cubature/get_ptr.h
jscatter/libs/cubature/_cubature.pyx
jscatter/libs/cubature/_test_integrands.pyx
jscatter/libs/cubature/__init__.py
jscatter/libs/cubature/get_ptr.c
jscatter/libs/cubature/test_cubature.py
jscatter/libs/cubature/_cubature.c
