Metadata-Version: 2.4
Name: jscatter
Version: 1.8.1
Summary: Combines dataArrays with attributes for fitting plotting and analysis including models for Xray and neutron scattering
Author-email: Ralf Biehl <ra.biehl@fz-juelich.de>
License-Expression: GPL-3.0-or-later
Project-URL: homepage, https://gitlab.com/biehl/jscatter
Project-URL: documentation, http://jscatter.readthedocs.io/
Project-URL: repository, https://gitlab.com/biehl/jscatter
Project-URL: live_demo, https://mybinder.org/v2/gl/biehl/jscatter/master?filepath=src/jscatter/examples/notebooks
Classifier: Development Status :: 5 - Production/Stable
Classifier: Intended Audience :: Science/Research
Classifier: Operating System :: POSIX :: Linux
Classifier: Operating System :: MacOS :: MacOS X
Classifier: Operating System :: Microsoft :: Windows :: Windows 10
Classifier: Programming Language :: Python :: 3.10
Classifier: Programming Language :: Python :: 3.11
Classifier: Programming Language :: Python :: 3.12
Classifier: Programming Language :: Python :: 3.13
Classifier: Programming Language :: Python :: 3.14
Classifier: Programming Language :: Python
Classifier: Topic :: Scientific/Engineering :: Physics
Requires-Python: >=3.9
License-File: src/jscatter/LICENSE
Requires-Dist: numpy>=2
Requires-Dist: scipy>=1.15.0
Requires-Dist: matplotlib>=3.7
Requires-Dist: Pillow>=8.1
Requires-Dist: MDAnalysis>=2.4.0
Requires-Dist: netcdf4
Requires-Dist: cython
Requires-Dist: fabio
Requires-Dist: pdb2pqr
Requires-Dist: requests
Requires-Dist: nglview
Requires-Dist: emcee
Dynamic: license-file
